errors/ReadError.py
pypl4/__init__.py
pypl4/pl4.py
pypl4/readPL4.py
pypl4-0.2.0.dist-info/METADATA
pypl4-0.2.0.dist-info/WHEEL
pypl4-0.2.0.dist-info/RECORD
