Metadata-Version: 2.1
Name: pypl4
Version: 0.2.0
Summary: O pacote pypl permite ler arquivos .pl4 e selecionar as oscilografias registradas nele.
License: GPL-3.0-only
Author: Mauricio
Author-email: mauricio_pavani@hotmail.com
Requires-Python: >=3.11,<4.0
Classifier: Environment :: Console
Classifier: License :: OSI Approved :: GNU General Public License v3 (GPLv3)
Classifier: Programming Language :: Python :: 3
Classifier: Programming Language :: Python :: 3.11
Classifier: Programming Language :: Python :: 3.12
Classifier: Topic :: Education
Requires-Dist: numpy (>=1.26.4,<2.0.0)
Project-URL: Bug Tracker, https://github.com/MauricioPavani/pypl4/issues
Project-URL: Código, https://github.com/MauricioPavani/pypl4
